device_communication/__init__.py
device_communication/_version.py
device_communication/base/__init__.py
device_communication/base/communication_handlers.py
device_communication/base/datatypes.py
device_communication/base/packetizer.py
device_communication/base/packets.py
device_communication/base/simulator.py
device_communication/serial/__init__.py
device_communication/serial/communication_handlers.py
device_communication/serial/packetizer.py
device_communication/serial/servers.py
device_communication/udp/__init__.py
device_communication/udp/communication_handlers.py
device_communication/udp/packetizer.py
device_communication/udp/servers.py
device_communication-0.2.0.dist-info/licenses/LICENSE
device_communication-0.2.0.dist-info/METADATA
device_communication-0.2.0.dist-info/WHEEL
device_communication-0.2.0.dist-info/top_level.txt
device_communication-0.2.0.dist-info/RECORD
