Metadata-Version: 2.4
Name: device-communication
Version: 0.2.0
Summary: Communication handlers over different mediums/protocols.
Maintainer-email: Piotr Sznapka <piotr.sznapka@int2code.com>
License: MIT License
Requires-Python: >=3.11
License-File: LICENSE
Requires-Dist: plum-py
Requires-Dist: pyserial
Provides-Extra: test
Requires-Dist: coverage; extra == "test"
Requires-Dist: pytest; extra == "test"
Requires-Dist: pytest-cov; extra == "test"
Requires-Dist: pytest-html; extra == "test"
Provides-Extra: dev
Requires-Dist: coverage; extra == "dev"
Requires-Dist: pytest; extra == "dev"
Requires-Dist: pytest-cov; extra == "dev"
Requires-Dist: pytest-html; extra == "dev"
Requires-Dist: black; extra == "dev"
Requires-Dist: pylint; extra == "dev"
Requires-Dist: tox; extra == "dev"
Provides-Extra: docs
Requires-Dist: coverage; extra == "docs"
Requires-Dist: pytest; extra == "docs"
Requires-Dist: pytest-cov; extra == "docs"
Requires-Dist: pytest-html; extra == "docs"
Requires-Dist: sphinx; extra == "docs"
Requires-Dist: sphinx-rtd-theme; extra == "docs"
Requires-Dist: sphinxcontrib-programoutput; extra == "docs"
Requires-Dist: myst-parser; extra == "docs"
Dynamic: license-file
